setup.py
nose_alembic_attrib/__init__.py
nose_alembic_attrib/alembic_attrib.py
nose_alembic_attrib.egg-info/PKG-INFO
nose_alembic_attrib.egg-info/SOURCES.txt
nose_alembic_attrib.egg-info/dependency_links.txt
nose_alembic_attrib.egg-info/entry_points.txt
nose_alembic_attrib.egg-info/requires.txt
nose_alembic_attrib.egg-info/top_level.txt