Metadata-Version: 1.0
Name: nose-alembic-attrib
Version: 0.1
Summary: Alembic attributes for nose
Home-page: https://github.com/jsok/nose-alembic-attrib
Author: Jonathan Sokolowski
Author-email: jonathan.sokolowski@gmail.com
License: BSD
Keywords: test nosetests nose nosetest plugin alembic sqlalchemy
Platform: UNKNOWN
Classifier: Programming Language :: Python
Classifier: Topic :: Software Development :: Testing
